university_ranking_scraper/__init__.py
university_ranking_scraper/constant.py
university_ranking_scraper-0.0.3.dist-info/METADATA
university_ranking_scraper-0.0.3.dist-info/WHEEL
university_ranking_scraper-0.0.3.dist-info/top_level.txt
university_ranking_scraper-0.0.3.dist-info/RECORD
