Metadata-Version: 2.4
Name: university_ranking_scraper
Version: 0.0.3
Summary: A web crawler to crawl Best Global University Ranking on usnews, Times Higher Education, and QS websites
Home-page: https://github.com/lowweihong/university_ranking_scraper
Author: Low Wei Hong
Author-email: M140042@e.ntu.edu.sg
Keywords: university_rankings,usnews,times_higher_education,qs
Classifier: Programming Language :: Python :: 3
Requires-Dist: pandas
Requires-Dist: httpx
Requires-Dist: lxml
Dynamic: author
Dynamic: author-email
Dynamic: classifier
Dynamic: description
Dynamic: description-content-type
Dynamic: home-page
Dynamic: keywords
Dynamic: requires-dist
Dynamic: summary
